espeakng/__init__.py
py_espeak_ng-0.1.8.dist-info/top_level.txt
py_espeak_ng-0.1.8.dist-info/METADATA
py_espeak_ng-0.1.8.dist-info/DESCRIPTION.rst
py_espeak_ng-0.1.8.dist-info/metadata.json
py_espeak_ng-0.1.8.dist-info/WHEEL
py_espeak_ng-0.1.8.dist-info/RECORD
