Metadata-Version: 1.1
Name: py-espeak-ng
Version: 0.1.8
Summary: Python interface for eSpeak NG
Home-page: https://github.com/gooofy/py-espeak-ng
Author: Guenter Bartsch
Author-email: guenter@zamia.org
License: Apache
Keywords: eSpeak NG TTS text to speech interface
Platform: Linux
Classifier: Topic :: Multimedia :: Sound/Audio :: Sound Synthesis
Classifier: Topic :: Multimedia :: Sound/Audio :: Speech
Classifier: Operating System :: POSIX :: Linux
Classifier: License :: OSI Approved :: Apache Software License
Classifier: Programming Language :: Python :: 2
Classifier: Programming Language :: Python :: 2.7
Classifier: Programming Language :: Python :: 3
Classifier: Programming Language :: Python :: 3.4
